[
    {
        "label": "CS",
        "value": "cs",
        "full_name": "Computer Science",
        "venues": [
            {
                "subdomain": "ai",
                "value": "ai",
                "label": "AI",
                "full_name": "Artificial Intelligence",
                "venues": [
                    {
                        "subsubdomain": "ml",
                        "value": "ml",
                        "label": "ML",
                        "full_name": "Machine Learning",
                        "venues": [
                            {
                                "label": "NeurIPS",
                                "value": "neurips",
                                "full_name": "Neural Information Processing Systems",
                                "places": [{
                                    "year": 2024,
                                    "location": "Vancouver, Canada"
                                }]
                            },
                            {
                                "label": "ICML",
                                "value": "icml",
                                "full_name": "International Conference on Machine Learning",
                                "places": [{
                                    "year": 2024,
                                    "location": "Vienna, Austria"
                                }]
                            },
                            {
                                "label": "ICLR",
                                "value": "iclr",
                                "full_name": "International Conference on Learning Representations",
                                "places": [{
                                    "year": 2024,
                                    "location": "Vienna, Austria"
                                }]
                            }
                        ]
                    },
                    {
                        "subsubdomain": "vision",
                        "value": "vision",
                        "label": "Vision",
                        "full_name": "Computer Vision",
                        "venues": [
                            {
                                "label": "CVPR",
                                "value": "cvpr",
                                "full_name": "Computer Vision and Pattern Recognition Conference",
                                "places": [{
                                    "year": 2024,
                                    "location": "Seattle, USA"
                                }]
                            },
                            {
                                "label": "WACV",
                                "value": "wacv",
                                "full_name": "Winter Conference on Applications of Computer Vision",
                                "places": [{
                                    "year": 2024,
                                    "location": "Hawaii, USA"
                                }]
                            },
                            {
                                "label": "ECCV",
                                "value": "eccv",
                                "full_name": "European Conference on Computer Vision",
                                "places": [{
                                    "year": 2024,
                                    "location": "Milan, Italy"
                                }]
                            }
                        ]
                    },
                    {
                        "subsubdomain": "nlp",
                        "value": "nlp",
                        "label": "NLP",
                        "full_name": "Natural Language Processing",
                        "venues": []
                    }
                ]
            },
            {
                "subdomain": "systems",
                "value": "systems",
                "label": "Systems",
                "full_name": "Systems and Networks",
                "venues": [
                    {
                        "subsubdomain": "mobilecomputing",
                        "value": "mobilecomputing",
                        "label": "Mobile Computing",
                        "full_name": "Mobile and Ubiquitous Computing",
                        "venues": [
                            {
                                "label": "MobiSys",
                                "value": "mobisys",
                                "full_name": "ACM International Conference on Mobile Systems, Applications, and Services",
                                "places": [{
                                    "year": 2024,
                                    "location": "Tokyo, Japan"
                                }]
                            }
                        ]
                    },
                    {
                        "subsubdomain": "databases",
                        "value": "databases",
                        "label": "Databases",
                        "full_name": "Databases",
                        "venues": [
                            {
                                "label": "VLDB",
                                "value": "vldb",
                                "full_name": "International Conference on Very Large Data Bases",
                                "places": [{
                                    "year": 2024,
                                    "location": "Guangzhou, China"
                                }]
                            }
                        ]
                    },
                    {
                        "subsubdomain": "operatingsystems",
                        "value": "operatingsystems",
                        "label": "Operating Systems",
                        "full_name": "Operating Systems",
                        "venues": [
                            {
                                "label": "OSDI",
                                "value": "osdi",
                                "full_name": "USENIX Symposium on Operating Systems Design and Implementation",
                                "places": [{
                                    "year": 2024,
                                    "location": "Santa Clara, USA"
                                }]
                            }
                        ]
                    },
                    {
                        "subsubdomain": "computernetworks",
                        "value": "computernetworks",
                        "label": "Computer Networks",
                        "full_name": "Computer Networks",
                        "venues": [
                            {
                                "label": "NSDI",
                                "value": "nsdi",
                                "full_name": "USENIX Symposium on Networked Systems Design and Implementation",
                                "places": [{
                                    "year": 2024,
                                    "location": "Santa Clara, USA"
                                }]
                            },
                            {
                                "label": "SIGCOMM",
                                "value": "sigcomm",
                                "full_name": "ACM Special Interest Group on Data Communication",
                                "places": [{
                                    "year": 2024,
                                    "location": "Sydney, Australia"
                                }]
                            }
                        ]
                    }
                ]
            },
            {
                "subdomain": "theory",
                "value": "theory",
                "label": "Theory",
                "full_name": "Theory",
                "venues": [
                    {
                        "subsubdomain": "algorithms",
                        "value": "algorithms",
                        "label": "Algorithms",
                        "full_name": "Algorithms and Complexity",
                        "venues": [
                            {
                                "label": "STOC",
                                "value": "stoc",
                                "full_name": "ACM Symposium on Theory of Computing",
                                "places": [{
                                    "year": 2024,
                                    "location": "Vancouver, Canada"
                                }]
                            },
                            {
                                "label": "FOCS",
                                "value": "focs",
                                "full_name": "IEEE Symposium on Foundations of Computer Science",
                                "places": [{
                                    "year": 2024,
                                    "location": "Chicago, USA"
                                }]
                            }
                        ]
                    }
                ]
            }
        ]
    },
    {
        "label": "Math",
        "value": "math",
        "full_name": "Math",
        "venues": []
    }        
]